ez_profile/__init__.py
ez_profile/profiler.py
ez_profile/snakeviz_launcher.py
ez_profile-0.1.0.dist-info/LICENSE
ez_profile-0.1.0.dist-info/METADATA
ez_profile-0.1.0.dist-info/WHEEL
ez_profile-0.1.0.dist-info/top_level.txt
ez_profile-0.1.0.dist-info/RECORD
