Metadata-Version: 2.1
Name: ez-profile
Version: 0.1.0
Summary: A basic wrapper around cProfile with optional snakeviz integration
Author: oddbookworm
License: MIT
License-File: LICENSE
